Workbook

Sheet FY 25-26 Summary
B1: Total | C1: Jul | D1: Aug | E1: Sep | F1: Oct | G1: Nov | H1: Dec | I1: Jan | J1: Feb | K1: Mar | L1: Apr | M1: May | N1: Jun
A2: No. of Jobs | B2: =SUM(C2:N2) -> 21 | C2: =COUNTIF('Staging Jobs'!$H$2:$H$58,C$1) -> 8 | D2: =COUNTIF('Staging Jobs'!$H$2:$H$58,D$1) -> 6 | E2: =COUNTIF('Staging Jobs'!$H$2:$H$58,E$1) -> 5 | F2: =COUNTIF('Staging Jobs'!$H$2:$H$58,F$1) -> 2 | G2: =COUNTIF('Staging Jobs'!$H$2:$H$58,G$1) -> 0 | H2: =COUNTIF('Staging Jobs'!$H$2:$H$58,H$1) -> 0 | I2: =COUNTIF('Staging Jobs'!$H$2:$H$58,I$1) -> 0 | J2: =COUNTIF('Staging Jobs'!$H$2:$H$58,J$1) -> 0 | ... N2: =COUNTIF('Staging Jobs'!$H$2:$H$58,N$1) -> 0
A3: Gross Invoice (incl. GST) | B3: =SUM(C3:N3) -> 60149.5 | C3: =SUMIFS('Staging Jobs'!$S$2:$S$58,'Staging Jobs'!$H$2:$H$58,C$1,'Staging Jobs'!$R$2:$R$58,"Y") -> 24230 | D3: =SUMIFS('Staging Jobs'!$S$2:$S$58,'Staging Jobs'!$H$2:$H$58,D$1,'Staging Jobs'!$R$2:$R$58,"Y") -> 15420 | E3: =SUMIFS('Staging Jobs'!$S$2:$S$58,'Staging Jobs'!$H$2:$H$58,E$1,'Staging Jobs'!$R$2:$R$58,"Y") -> 16999.5 | F3: =SUMIFS('Staging Jobs'!$S$2:$S$58,'Staging Jobs'!$H$2:$H$58,F$1,'Staging Jobs'!$R$2:$R$58,"Y") -> 3500 | G3: =SUMIFS('Staging Jobs'!$S$2:$S$58,'Staging Jobs'!$H$2:$H$58,G$1,'Staging Jobs'!$R$2:$R$58,"Y") -> 0 | H3: =SUMIFS('Staging Jobs'!$S$2:$S$58,'Staging Jobs'!$H$2:$H$58,H$1,'Staging Jobs'!$R$2:$R$58,"Y") -> 0 | I3: =SUMIFS('Staging Jobs'!$S$2:$S$58,'Staging Jobs'!$H$2:$H$58,I$1,'Staging Jobs'!$R$2:$R$58,"Y") -> 0 | J3: =SUMIFS('Staging Jobs'!$S$2:$S$58,'Staging Jobs'!$H$2:$H$58,J$1,'Staging Jobs'!$R$2:$R$58,"Y") -> 0 | ... N3: =SUMIFS('Staging Jobs'!$S$2:$S$58,'Staging Jobs'!$H$2:$H$58,N$1,'Staging Jobs'!$R$2:$R$58,"Y") -> 0
A4: Transport (incl. GST) | B4: =SUM(C4:N4) -> 10179 | C4: =SUMIF('Staging Jobs'!$H$2:$H$58,C$1,'Staging Jobs'!$AD$2:$AD$58)+ SUMIF('Transport Only'!$B$4:$B$102,C$1,'Transport Only'!$H$4:$H$102) -> 3817 | D4: =SUMIF('Staging Jobs'!$H$2:$H$58,D$1,'Staging Jobs'!$AD$2:$AD$58)+ SUMIF('Transport Only'!$B$4:$B$102,D$1,'Transport Only'!$H$4:$H$102) -> 2475 | E4: =SUMIF('Staging Jobs'!$H$2:$H$58,E$1,'Staging Jobs'!$AD$2:$AD$58)+ SUMIF('Transport Only'!$B$4:$B$102,E$1,'Transport Only'!$H$4:$H$102) -> 2875 | F4: =SUMIF('Staging Jobs'!$H$2:$H$58,F$1,'Staging Jobs'!$AD$2:$AD$58)+ SUMIF('Transport Only'!$B$4:$B$102,F$1,'Transport Only'!$H$4:$H$102) -> 682 | G4: =SUMIF('Staging Jobs'!$H$2:$H$58,G$1,'Staging Jobs'!$AD$2:$AD$58)+ SUMIF('Transport Only'!$B$4:$B$102,G$1,'Transport Only'!$H$4:$H$102) -> 330 | H4: =SUMIF('Staging Jobs'!$H$2:$H$58,H$1,'Staging Jobs'!$AD$2:$AD$58)+ SUMIF('Transport Only'!$B$4:$B$102,H$1,'Transport Only'!$H$4:$H$102) -> 0 | I4: =SUMIF('Staging Jobs'!$H$2:$H$58,I$1,'Staging Jobs'!$AD$2:$AD$58)+ SUMIF('Transport Only'!$B$4:$B$102,I$1,'Transport Only'!$H$4:$H$102) -> 0 | J4: =SUMIF('Staging Jobs'!$H$2:$H$58,J$1,'Staging Jobs'!$AD$2:$AD$58)+ SUMIF('Transport Only'!$B$4:$B$102,J$1,'Transport Only'!$H$4:$H$102) -> 0 | ... N4: =SUMIF('Staging Jobs'!$H$2:$H$58,N$1,'Staging Jobs'!$AD$2:$AD$58)+ SUMIF('Transport Only'!$B$4:$B$102,N$1,'Transport Only'!$H$4:$H$102) -> 0
A5: Total GST | B5: =SUM(C5:N5) -> 6108.9545 | C5: =SUMIFS('Staging Jobs'!$T$2:$T$58,'Staging Jobs'!$H$2:$H$58,C$1,'Staging Jobs'!$R$2:$R$58,"Y")+ SUMIFS('Staging Jobs'!$AE$2:$AE$58,'Staging Jobs'!$H$2:$H$58,C$1,'Staging Jobs'!$AF$2:$AF$58,"Y")+ SUMIFS('Transport Only'!$I$4:$I$102,'Transport Only'!$B$4:$B$102,C$1,'Transport Only'!$J$4:$J$102,"Y") -> 2549.7273 | D5: =SUMIFS('Staging Jobs'!$T$2:$T$58,'Staging Jobs'!$H$2:$H$58,D$1,'Staging Jobs'!$R$2:$R$58,"Y")+ SUMIFS('Staging Jobs'!$AE$2:$AE$58,'Staging Jobs'!$H$2:$H$58,D$1,'Staging Jobs'!$AF$2:$AF$58,"Y")+ SUMIFS('Transport Only'!$I$4:$I$102,'Transport Only'!$B$4:$B$102,D$1,'Transport Only'!$J$4:$J$102,"Y") -> 1372.2727 | E5: =SUMIFS('Staging Jobs'!$T$2:$T$58,'Staging Jobs'!$H$2:$H$58,E$1,'Staging Jobs'!$R$2:$R$58,"Y")+ SUMIFS('Staging Jobs'!$AE$2:$AE$58,'Staging Jobs'!$H$2:$H$58,E$1,'Staging Jobs'!$AF$2:$AF$58,"Y")+ SUMIFS('Transport Only'!$I$4:$I$102,'Transport Only'!$B$4:$B$102,E$1,'Transport Only'!$J$4:$J$102,"Y") -> 1806.7727 | F5: =SUMIFS('Staging Jobs'!$T$2:$T$58,'Staging Jobs'!$H$2:$H$58,F$1,'Staging Jobs'!$R$2:$R$58,"Y")+ SUMIFS('Staging Jobs'!$AE$2:$AE$58,'Staging Jobs'!$H$2:$H$58,F$1,'Staging Jobs'!$AF$2:$AF$58,"Y")+ SUMIFS('Transport Only'!$I$4:$I$102,'Transport Only'!$B$4:$B$102,F$1,'Transport Only'!$J$4:$J$102,"Y") -> 380.18182 | G5: =SUMIFS('Staging Jobs'!$T$2:$T$58,'Staging Jobs'!$H$2:$H$58,G$1,'Staging Jobs'!$R$2:$R$58,"Y")+ SUMIFS('Staging Jobs'!$AE$2:$AE$58,'Staging Jobs'!$H$2:$H$58,G$1,'Staging Jobs'!$AF$2:$AF$58,"Y")+ SUMIFS('Transport Only'!$I$4:$I$102,'Transport Only'!$B$4:$B$102,G$1,'Transport Only'!$J$4:$J$102,"Y") -> 0 | H5: =SUMIFS('Staging Jobs'!$T$2:$T$58,'Staging Jobs'!$H$2:$H$58,H$1,'Staging Jobs'!$R$2:$R$58,"Y")+ SUMIFS('Staging Jobs'!$AE$2:$AE$58,'Staging Jobs'!$H$2:$H$58,H$1,'Staging Jobs'!$AF$2:$AF$58,"Y")+ SUMIFS('Transport Only'!$I$4:$I$102,'Transport Only'!$B$4:$B$102,H$1,'Transport Only'!$J$4:$J$102,"Y") -> 0 | I5: =SUMIFS('Staging Jobs'!$T$2:$T$58,'Staging Jobs'!$H$2:$H$58,I$1,'Staging Jobs'!$R$2:$R$58,"Y")+ SUMIFS('Staging Jobs'!$AE$2:$AE$58,'Staging Jobs'!$H$2:$H$58,I$1,'Staging Jobs'!$AF$2:$AF$58,"Y")+ SUMIFS('Transport Only'!$I$4:$I$102,'Transport Only'!$B$4:$B$102,I$1,'Transport Only'!$J$4:$J$102,"Y") -> 0 | J5: =SUMIFS('Staging Jobs'!$T$2:$T$58,'Staging Jobs'!$H$2:$H$58,J$1,'Staging Jobs'!$R$2:$R$58,"Y")+ SUMIFS('Staging Jobs'!$AE$2:$AE$58,'Staging Jobs'!$H$2:$H$58,J$1,'Staging Jobs'!$AF$2:$AF$58,"Y")+ SUMIFS('Transport Only'!$I$4:$I$102,'Transport Only'!$B$4:$B$102,J$1,'Transport Only'!$J$4:$J$102,"Y") -> 0 | ... N5: =SUMIFS('Staging Jobs'!$T$2:$T$58,'Staging Jobs'!$H$2:$H$58,N$1,'Staging Jobs'!$R$2:$R$58,"Y")+ SUMIFS('Staging Jobs'!$AE$2:$AE$58,'Staging Jobs'!$H$2:$H$58,N$1,'Staging Jobs'!$AF$2:$AF$58,"Y")+ SUMIFS('Transport Only'!$I$4:$I$102,'Transport Only'!$B$4:$B$102,N$1,'Transport Only'!$J$4:$J$102,"Y") -> 0
A6: Total Referral Paid | B6: =SUM(C6:N6) -> 3258.5909 | C6: =SUMIFS('Staging Jobs'!$W$2:$W$58,'Staging Jobs'!$H$2:$H$58,C$1,'Staging Jobs'!$R$2:$R$58,"Y") -> 1244.0909 | D6: =SUMIFS('Staging Jobs'!$W$2:$W$58,'Staging Jobs'!$H$2:$H$58,D$1,'Staging Jobs'!$R$2:$R$58,"Y") -> 1190.9091 | E6: =SUMIFS('Staging Jobs'!$W$2:$W$58,'Staging Jobs'!$H$2:$H$58,E$1,'Staging Jobs'!$R$2:$R$58,"Y") -> 823.59091 | F6: =SUMIFS('Staging Jobs'!$W$2:$W$58,'Staging Jobs'!$H$2:$H$58,F$1,'Staging Jobs'!$R$2:$R$58,"Y") -> 0 | G6: =SUMIFS('Staging Jobs'!$W$2:$W$58,'Staging Jobs'!$H$2:$H$58,G$1,'Staging Jobs'!$R$2:$R$58,"Y") -> 0 | H6: =SUMIFS('Staging Jobs'!$W$2:$W$58,'Staging Jobs'!$H$2:$H$58,H$1,'Staging Jobs'!$R$2:$R$58,"Y") -> 0 | I6: =SUMIFS('Staging Jobs'!$W$2:$W$58,'Staging Jobs'!$H$2:$H$58,I$1,'Staging Jobs'!$R$2:$R$58,"Y") -> 0 | J6: =SUMIFS('Staging Jobs'!$W$2:$W$58,'Staging Jobs'!$H$2:$H$58,J$1,'Staging Jobs'!$R$2:$R$58,"Y") -> 0 | ... N6: =SUMIFS('Staging Jobs'!$W$2:$W$58,'Staging Jobs'!$H$2:$H$58,N$1,'Staging Jobs'!$R$2:$R$58,"Y") -> 0
A8: Net Sales | B8: =B3-B4-B5-B6 -> 40602.955 | C8: =C3-C4-C5-C6 -> 16619.182 | D8: =D3-D4-D5-D6 -> 10381.818 | E8: =E3-E4-E5-E6 -> 11494.136 | F8: =F3-F4-F5-F6 -> 2437.8182 | G8: =G3-G4-G5-G6 -> -330 | H8: =H3-H4-H5-H6 -> 0 | I8: =I3-I4-I5-I6 -> 0 | ... N8: =N3-N4-N5-N6 -> 0
B9: =B8/B3 -> 0.67503395 | C9: =C8/C3 -> 0.68589277 | D9: =D8/D3 -> 0.67326966 | E9: =E8/E3 -> 0.67614556 | F9: =F8/F3 -> 0.69651948 | G9: =G8/G3 -> #DIV/0! | H9: =H8/H3 -> #DIV/0! | I9: =I8/I3 -> #DIV/0! | ... N9: =N8/N3 -> #DIV/0!
A11: Transport yet to be Paid | B11: =SUMIF('Staging Jobs'!$AF$2:$AF$58,"",'Staging Jobs'!$AD$2:$AD$58)+ SUMIF('Transport Only'!$J$4:$J$102,"",'Transport Only'!$H$4:$H$102) -> 330

Sheet Costing
A1: Quote No | B1: Address | C1: Suburb | D1: Client Name | E1: Agent Name | F1: Agent | G1: Master Bedroom | H1: Guest Bedroom | I1: Living | J1: Dining | K1: Kitchen | L1: Alfresco | M1: Bath | N1: Hallway Table | O1: Study | P1: Small Living | Q1: Sold in Weeks | R1: Payment Type | S1: invoice Paid (Y/N) | T1: Gross | U1: GST | V1: Net | W1: Referral (Y/N) | X1: Referral Amount | Y1: Referral Paid | Z1: Truck | AA1: Time In | AB1: Time Out | AC1: Call Out Fee | AD1: Total Hours | AE1: Gross | AF1: GST | AG1: Paid | AH1: Invoice No, | AI1: Comments
A2: 1 | B2: 80 Lakewood Bvd | C2: Melton | E2: Aman Sandhu | F2: YPA, Point Cook
A3: 2 | B3: 6 Hutchison Rd | C3: Mambourin | E3: Amit Yadhav | F3: Engage Real Estate
A4: 3 | B4: 2/2 Manoon Rd | C4: Clayton South | E4: Michael Renzella | F4: Ray White, Clayton
A5: 4 | B5: 2/16 Risdon Drive | C5: Notting Hill | E5: Michael Renzella | F5: Ray White, Clayton
A6: 5 | B6: 12 Hardy Ct | C6: Oakleigh South | E6: Elroy Malowney | F6: Ray White, Oakleigh
A7: 6 | B7: 10 Hound St | C7: Wyndham Vale | E7: Mahesh Krishna | F7: Eview Real Estate
A8: 7 | B8: 6 Kinglake Dr | C8: Manor Lakes | E8: Mahesh Krishna | F8: Eview Real Estate
A9: 8 | B9: 2/59 Jaguar Dr | C9: Clayton | E9: Michael Renzella | F9: Ray White, Clayton
A10: 9 | B10: 42 Jackson Green Bvd | C10: Clayton South | E10: Jie Zhou | F10: Ray White, Oakleigh
A11: 10 | B11: 401 Maracana Ave | C11: Manor Lakes | E11: Mahesh Krishna | F11: Eview Real Estate
A12: 11 | B12: 2/32 Alice St | C12: Clayton | E12: Michael Renzella | F12: Ray White, Clayton
A13: 12 | B13: 2/2 Stewart Rd | C13: Oakleigh East | E13: Elroy Malowney | F13: Ray White, Oakleigh
... A22: 21 | B22: 1/18 Wordsworth Ave | C22: Clayton South | E22: Michael Renzella | F22: Ray White, Clayton

Sheet Staging Jobs
A1: No. of Jobs | B1: Address | C1: Suburb | D1: Agent | E1: Agent Name | F1: Staged Date | G1: Advertised Date | H1: Month | I1: Proposed Project Completion Date | J1: Staging Removed Date | K1: Auction/ Private Sale | L1: Auction/ Sold Date | M1: Price Min | N1: Price Max | O1: Sold Price | P1: Sold in Weeks | Q1: Payment Type | R1: invoice Paid (Y/N) | S1: Gross | T1: GST | U1: Net | V1: Referral (Y/N) | W1: Referral Amount | X1: Referral Paid | Y1: Truck | Z1: Time In | AA1: Time Out | AB1: Call Out Fee | AC1: Total Hours | AD1: Gross | AE1: GST | AF1: Paid | AG1: Invoice No, | AH1: Comments
A2: 1 | B2: 80 Lakewood Bvd | C2: Melton | D2: YPA, Point Cook | E2: Aman Sandhu | F2: 45843 | G2: 45849 | H2: =IF(F2="","",TEXT(F2,"MMM")) -> Jul | I2: =F2+56 -> 45899 | J2: 45886 | K2: Private | L2: 45878 | M2: 599000 | N2: 649000 | O2: 601000 | P2: =IF(L2="","",(L2-G2)/7) -> 4.1428571 | Q2: EFT | R2: Y | S2: 2800 | T2: =IF(S2="","",IF(Q2="EFT",S2/11,"")) -> 254.54545 | U2: =IF(T2="",S2,S2-T2) -> 2545.4545 | V2: N | W2: =IF(V2="Y",U2*0.1,"") | Y2: Small | Z2: 0.375 | AA2: 0.5 | AB2: Y | AC2: =IF(AB2="Y",(AA2-Z2)+(0.5/24),(AA2-Z2)) -> 0.14583333 | AD2: =IF(Y2="small",AC2*24*$AN$2,AC2*24*$AO$2) -> 385 | AE2: =IF(AD2="","",AD2/11) -> 35 | AF2: Y | AG2: 00223 | AM2: Rate/hr | AN2: 110 | AO2: 143
A3: 2 | B3: 6 Hutchison Rd | C3: Mambourin | D3: Engage Real Estate | E3: Amit Yadhav | F3: 45843 | G3: 45849 | H3: =IF(F3="","",TEXT(F3,"MMM")) -> Jul | I3: =F3+56 -> 45899 | K3: Private | M3: 680000 | N3: 720000 | P3: =IF(L3="","",(L3-G3)/7) | Q3: EFT | R3: Y | S3: 2750 | T3: =IF(S3="","",IF(Q3="EFT",S3/11,"")) -> 250 | U3: =IF(T3="",S3,S3-T3) -> 2500 | V3: Y | W3: =IF(V3="Y",U3*0.05,"") -> 125 | X3: Y | Y3: Small | Z3: 0.625 | AA3: 0.70833333 | AB3: N | AC3: =IF(AB3="Y",(AA3-Z3)+(0.5/24),(AA3-Z3)) -> 0.083333333 | AD3: =IF(Y3="small",AC3*24*$AN$2,AC3*24*$AO$2) -> 220 | AE3: =IF(AD3="","",AD3/11) -> 20 | AF3: Y | AG3: 00223
A4: 3 | B4: 2/2 Manoon Rd | C4: Clayton South | D4: Ray White, Clayton | E4: Michael Renzella | F4: 45847 | G4: 45852 | H4: =IF(F4="","",TEXT(F4,"MMM")) -> Jul | I4: =F4+56 -> 45903 | J4: 45903 | K4: Auction | L4: 45885 | M4: 780000 | N4: 850000 | O4: 930000 | P4: =IF(L4="","",(L4-G4)/7) -> 4.7142857 | Q4: EFT | R4: Y | S4: 2970 | T4: =IF(S4="","",IF(Q4="EFT",S4/11,"")) -> 270 | U4: =IF(T4="",S4,S4-T4) -> 2700 | V4: Y | W4: =IF(V4="Y",U4*0.1,"") -> 270 | X4: Y | Y4: Small | Z4: 0.79166667 | AA4: 0.875 | AB4: Y | AC4: =IF(AB4="Y",(AA4-Z4)+(0.5/24),(AA4-Z4)) -> 0.10416667 | AD4: =IF(Y4="small",AC4*24*$AN$2,AC4*24*$AO$2) -> 275 | AE4: =IF(AD4="","",AD4/11) -> 25 | AF4: Y | AG4: 00223
A5: 4 | B5: 2/16 Risdon Drive | C5: Notting Hill | D5: Ray White, Clayton | E5: Michael Renzella | F5: 45855 | G5: 45861 | H5: =IF(F5="","",TEXT(F5,"MMM")) -> Jul | I5: =F5+56 -> 45911 | J5: 45921 | K5: Private | L5: 45903 | M5: 980000 | N5: 105000 | O5: 998000 | P5: =IF(L5="","",(L5-G5)/7) -> 6 | Q5: EFT | R5: Y | S5: 2900 | T5: =IF(S5="","",IF(Q5="EFT",S5/11,"")) -> 263.63636 | U5: =IF(T5="",S5,S5-T5) -> 2636.3636 | V5: Y | W5: =IF(V5="Y",U5*0.1,"") -> 263.63636 | X5: Y | Y5: Small | Z5: 0.39583333 | AA5: 0.5 | AB5: Y | AC5: =IF(AB5="Y",(AA5-Z5)+(0.5/24),(AA5-Z5)) -> 0.125 | AD5: =IF(Y5="small",AC5*24*$AN$2,AC5*24*$AO$2) -> 330 | AE5: =IF(AD5="","",AD5/11) -> 30 | AF5: Y | AG5: 00223
A6: 5 | B6: 12 Hardy Ct | C6: Oakleigh South | D6: Ray White, Oakleigh | E6: Elroy Malowney | F6: 45858 | G6: 45863 | H6: =IF(F6="","",TEXT(F6,"MMM")) -> Jul | I6: =F6+56 -> 45914 | J6: 45892 | K6: Auction | L6: 45885 | M6: 870000 | N6: 950000 | O6: 1321000 | P6: =IF(L6="","",(L6-G6)/7) -> 3.1428571 | Q6: EFT | R6: Y | S6: 2970 | T6: =IF(S6="","",IF(Q6="EFT",S6/11,"")) -> 270 | U6: =IF(T6="",S6,S6-T6) -> 2700 | V6: Y | W6: =IF(V6="Y",U6*0.1,"") -> 270 | X6: Y | Y6: Small | AC6: =IF(AB6="Y",(AA6-Z6)+(0.5/24),(AA6-Z6)) -> 0 | AD6: =IF(Y6="small",AC6*24*$AN$2,AC6*24*$AO$2) -> 0 | AE6: =IF(AD6="","",AD6/11) -> 0 | AF6: Y | AG6: 00223 | AH6: Transported together with 10 Hound St, Wyndham Vale
A7: 6 | B7: 10 Hound St | C7: Wyndham Vale | D7: Eview Real Estate | E7: Mahesh Krishna | F7: 45859 | G7: 45863 | H7: =IF(F7="","",TEXT(F7,"MMM")) -> Jul | I7: =F7+56 -> 45915 | J7: 45962 | K7: Private | L7: 45931 | M7: 720000 | N7: 760000 | O7: 720000 | P7: =IF(L7="","",(L7-G7)/7) -> 9.7142857 | Q7: EFT | R7: Y | S7: 2900 | T7: =IF(S7="","",IF(Q7="EFT",S7/11,"")) -> 263.63636 | U7: =IF(T7="",S7,S7-T7) -> 2636.3636 | V7: N | W7: =IF(V7="Y",U7*0.1,"") | Y7: Small | Z7: 0.4375 | AA7: 0.60416667 | AB7: Y | AC7: =IF(AB7="Y",(AA7-Z7)+(0.5/24),(AA7-Z7)) -> 0.1875 | AD7: =IF(Y7="small",AC7*24*$AN$2,AC7*24*$AO$2) -> 495 | AE7: =IF(AD7="","",AD7/11) -> 45 | AF7: Y | AG7: 00223
A8: 7 | B8: 6 Kinglake Dr | C8: Manor Lakes | D8: Eview Real Estate | E8: Mahesh Krishna | F8: 45861 | G8: 45863 | H8: =IF(F8="","",TEXT(F8,"MMM")) -> Jul | I8: =F8+56 -> 45917 | J8: 45926 | K8: Private | L8: 45911 | M8: 740000 | N8: 760000 | O8: 720000 | P8: =IF(L8="","",(L8-G8)/7) -> 6.8571429 | Q8: EFT | R8: Y | S8: 3470 | T8: =IF(S8="","",IF(Q8="EFT",S8/11,"")) -> 315.45455 | U8: =IF(T8="",S8,S8-T8) -> 3154.5455 | V8: N | W8: =IF(V8="Y",U8*0.1,"") | Y8: Small | Z8: 0.083333333 | AA8: 0.27083333 | AB8: Y | AC8: =IF(AB8="Y",(AA8-Z8)+(0.5/24),(AA8-Z8)) -> 0.20833333 | AD8: =IF(Y8="small",AC8*24*$AN$2,AC8*24*$AO$2) -> 550 | AE8: =IF(AD8="","",AD8/11) -> 50 | AF8: Y | AG8: 00223
A9: 8 | B9: 2/59 Jaguar Dr | C9: Clayton | D9: Ray White, Clayton | E9: Michael Renzella | F9: 45868 | G9: 45870 | H9: =IF(F9="","",TEXT(F9,"MMM")) -> Jul | I9: =F9+56 -> 45924 | J9: 45919 | K9: Auction | L9: 45903 | M9: 900000 | N9: 990000 | O9: 1100000 | P9: =IF(L9="","",(L9-G9)/7) -> 4.7142857 | Q9: EFT | R9: Y | S9: 3470 | T9: =IF(S9="","",IF(Q9="EFT",S9/11,"")) -> 315.45455 | U9: =IF(T9="",S9,S9-T9) -> 3154.5455 | V9: Y | W9: =IF(V9="Y",U9*0.1,"") -> 315.45455 | X9: Y | Y9: Small | Z9: 0.58333333 | AA9: 0.66666667 | AB9: Y | AC9: =IF(AB9="Y",(AA9-Z9)+(0.5/24),(AA9-Z9)) -> 0.10416667 | AD9: =IF(Y9="small",AC9*24*$AN$2,AC9*24*$AO$2) -> 275 | AE9: =IF(AD9="","",AD9/11) -> 25 | AF9: Y | AG9: 00226
A10: 9 | B10: 42 Jackson Green Bvd | C10: Clayton South | D10: Ray White, Oakleigh | E10: Jie Zhou | F10: 45870 | G10: 45884 | H10: =IF(F10="","",TEXT(F10,"MMM")) -> Aug | I10: =F10+56 -> 45926 | J10: 45930 | K10: Auction | L10: 45913 | M10: 680000 | N10: 740000 | O10: 812000 | P10: =IF(L10="","",(L10-G10)/7) -> 4.1428571 | Q10: EFT | R10: Y | S10: 2640 | T10: =IF(S10="","",IF(Q10="EFT",S10/11,"")) -> 240 | U10: =IF(T10="",S10,S10-T10) -> 2400 | V10: Y | W10: =IF(V10="Y",U10*0.1,"") -> 240 | X10: Y | Y10: Small | Z10: 0.52083333 | AA10: 0.60416667 | AB10: Y | AC10: =IF(AB10="Y",(AA10-Z10)+(0.5/24),(AA10-Z10)) -> 0.10416667 | AD10: =IF(Y10="small",AC10*24*$AN$2,AC10*24*$AO$2) -> 275 | AE10: =IF(AD10="","",AD10/11) -> 25 | AF10: Y | AG10: 00226
A11: 10 | B11: 401 Maracana Ave | C11: Manor Lakes | D11: Eview Real Estate | E11: Mahesh Krishna | F11: 45871 | G11: 45875 | H11: =IF(F11="","",TEXT(F11,"MMM")) -> Aug | I11: =F11+56 -> 45927 | J11: 45938 | K11: Private | L11: 45901 | M11: 630000 | N11: 680000 | O11: 660000 | P11: =IF(L11="","",(L11-G11)/7) -> 3.7142857 | Q11: EFT | R11: Y | S11: 2600 | T11: =IF(S11="","",IF(Q11="EFT",S11/11,"")) -> 236.36364 | U11: =IF(T11="",S11,S11-T11) -> 2363.6364 | V11: N | W11: =IF(V11="Y",U11*0.1,"") | Y11: Small | Z11: 0.54166667 | AA11: 0.6875 | AB11: Y | AC11: =IF(AB11="Y",(AA11-Z11)+(0.5/24),(AA11-Z11)) -> 0.16666667 | AD11: =IF(Y11="small",AC11*24*$AN$2,AC11*24*$AO$2) -> 440 | AE11: =IF(AD11="","",AD11/11) -> 40 | AF11: Y | AG11: 00226
A12: 11 | B12: 2/32 Alice St | C12: Clayton | D12: Ray White, Clayton | E12: Michael Renzella | F12: 45873 | G12: 45875 | H12: =IF(F12="","",TEXT(F12,"MMM")) -> Aug | I12: =F12+56 -> 45929 | J12: 45919 | K12: Auction | L12: 45899 | M12: 1000000 | N12: 1100000 | O12: 1165000 | P12: =IF(L12="","",(L12-G12)/7) -> 3.4285714 | Q12: Cash | R12: Y | S12: 2800 | T12: =IF(S12="","",IF(Q12="EFT",S12/11,"")) | U12: =IF(T12="",S12,S12-T12) -> 2800 | V12: Y | W12: =IF(V12="Y",U12*0.1,"") -> 280 | X12: Y | Y12: Small | Z12: 0.41666667 | AA12: 0.52083333 | AB12: Y | AC12: =IF(AB12="Y",(AA12-Z12)+(0.5/24),(AA12-Z12)) -> 0.125 | AD12: =IF(Y12="small",AC12*24*$AN$2,AC12*24*$AO$2) -> 330 | AE12: =IF(AD12="","",AD12/11) -> 30 | AF12: Y | AG12: 00226
A13: 12 | B13: 2/2 Stewart Rd | C13: Oakleigh East | D13: Ray White, Oakleigh | E13: Elroy Malowney | F13: 45875 | G13: 45877 | H13: =IF(F13="","",TEXT(F13,"MMM")) -> Aug | I13: =F13+56 -> 45931 | J13: 45932 | K13: Auction | L13: 45900 | M13: 800000 | N13: 880000 | O13: 892500 | P13: =IF(L13="","",(L13-G13)/7) -> 3.2857143 | Q13: EFT | R13: Y | S13: 2310 | T13: =IF(S13="","",IF(Q13="EFT",S13/11,"")) -> 210 | U13: =IF(T13="",S13,S13-T13) -> 2100 | V13: Y | W13: =IF(V13="Y",U13*0.1,"") -> 210 | X13: Y | Y13: Small | Z13: 0.41666667 | AA13: 0.625 | AB13: Y | AC13: =IF(AB13="Y",(AA13-Z13)+(0.5/24),(AA13-Z13)) -> 0.22916667 | AD13: =IF(Y13="small",AC13*24*$AN$2,AC13*24*$AO$2) -> 605 | AE13: =IF(AD13="","",AD13/11) -> 55 | AF13: Y | AG13: 00226
A14: 13 | B14: 2/47 Margaret St | C14: Clayton | D14: Ray White, Oakleigh | E14: Elroy Malowney | F14: 45875 | G14: 45877 | H14: =IF(F14="","",TEXT(F14,"MMM")) -> Aug | I14: =F14+56 -> 45931 | J14: 45932 | K14: Auction | L14: 45899 | M14: 830000 | N14: 910000 | O14: 1000000 | P14: =IF(L14="","",(L14-G14)/7) -> 3.1428571 | Q14: EFT | R14: Y | S14: 3470 | T14: =IF(S14="","",IF(Q14="EFT",S14/11,"")) -> 315.45455 | U14: =IF(T14="",S14,S14-T14) -> 3154.5455 | V14: Y | W14: =IF(V14="Y",U14*0.1,"") -> 315.45455 | X14: Y | Y14: Small | AC14: =IF(AB14="Y",(AA14-Z14)+(0.5/24),(AA14-Z14)) -> 0 | AD14: =IF(Y14="small",AC14*24*$AN$2,AC14*24*$AO$2) -> 0 | AE14: =IF(AD14="","",AD14/11) -> 0 | AF14: Y | AH14: Transport together with Stewart Rd
A15: 14 | B15: 4b Thompson St | C15: Clayton | D15: Ray White, Clayton | E15: Michael Renzella | F15: 45886 | G15: 45895 | H15: =IF(F15="","",TEXT(F15,"MMM")) -> Aug | I15: =F15+56 -> 45942 | J15: 45932 | K15: Auction | L15: 45920 | M15: 780000 | N15: 850000 | O15: 988000 | P15: =IF(L15="","",(L15-G15)/7) -> 3.5714286 | Q15: EFT | R15: Y | S15: 1600 | T15: =IF(S15="","",IF(Q15="EFT",S15/11,"")) -> 145.45455 | U15: =IF(T15="",S15,S15-T15) -> 1454.5455 | V15: Y | W15: =IF(V15="Y",U15*0.1,"") -> 145.45455 | Y15: Small | AB15: Y | AC15: 0.20833333 | AD15: =IF(Y15="small",AC15*24*$AN$2,AC15*24*$AO$2) -> 550 | AE15: =IF(AD15="","",AD15/11) -> 50 | AF15: Y
A16: 15 | B16: 17/194 Alma Rd | C16: St. Kilda East | D16: McGrath Estate Agents | E16: Melanie Walden | F16: 45903 | G16: 45912 | H16: =IF(F16="","",TEXT(F16,"MMM")) -> Sep | I16: =F16+56 -> 45959 | K16: Private | M16: 600000 | N16: 639000 | Q16: EFT | R16: Y | S16: 3040 | T16: =IF(S16="","",IF(Q16="EFT",S16/11,"")) -> 276.36364 | U16: =IF(T16="",S16,S16-T16) -> 2763.6364 | V16: N | W16: =IF(V16="Y",U16*0.1,"") | Y16: Small | Z16: 0.64583333 | AA16: 0.79166667 | AB16: Y | AC16: =IF(AB16="Y",(AA16-Z16)+(0.5/24),(AA16-Z16)) -> 0.16666667 | AD16: =IF(Y16="small",AC16*24*$AN$2,AC16*24*$AO$2) -> 440 | AE16: =IF(AD16="","",AD16/11) -> 40 | AF16: Y
A17: 16 | B17: 5/1254 Centre Rd | C17: Clayton | D17: Ray White, Clayton | E17: Shanky Walia | F17: 45919 | G17: 13050 | H17: =IF(F17="","",TEXT(F17,"MMM")) -> Sep | I17: =F17+56 -> 45975 | J17: 45959 | K17: Auction | L17: 45948 | M17: 520000 | N17: 570000 | O17: 639000 | Q17: EFT | R17: Y | S17: 1950 | T17: =IF(S17="","",IF(Q17="EFT",S17/11,"")) -> 177.27273 | U17: =IF(T17="",S17,S17-T17) -> 1772.7273 | V17: Y | W17: =IF(V17="Y",U17*0.1,"") -> 177.27273 | X17: Y | Y17: Small | Z17: 0.39583333 | AA17: 0.625 | AB17: Y | AC17: =IF(AB17="Y",(AA17-Z17)+(0.5/24),(AA17-Z17)) -> 0.25 | AD17: =IF(Y17="small",AC17*24*$AN$2,AC17*24*$AO$2) -> 660 | AE17: =IF(AD17="","",AD17/11) -> 60 | AF17: Y
A18: 17 | B18: 7 Kitson Rd | C18: Clayton South | D18: Ray White, Clayton | E18: Michael Renzella | F18: 45919 | G18: 45924 | H18: =IF(F18="","",TEXT(F18,"MMM")) -> Sep | I18: =F18+56 -> 45975 | K18: Auction | L18: 45948 | M18: 980000 | N18: 1050000 | O18: 1120000 | Q18: EFT | R18: Y | S18: 4339.5 | T18: =IF(S18="","",IF(Q18="EFT",S18/11,"")) -> 394.5 | U18: =IF(T18="",S18,S18-T18) -> 3945 | V18: Y | W18: =IF(V18="Y",U18*0.1,"") -> 394.5 | X18: Y | Y18: Small | AC18: =IF(AB18="Y",(AA18-Z18)+(0.5/24),(AA18-Z18)) -> 0 | AD18: =IF(Y18="small",AC18*24*$AN$2,AC18*24*$AO$2) -> 0 | AE18: =IF(AD18="","",AD18/11) -> 0 | AF18: Y | AH18: Transport together with Centre Rd
A19: 18 | B19: 30 Landing Place | C19: Point Cook | D19: CHN Real Estate | E19: Luke | F19: 45926 | G19: 45932 | H19: =IF(F19="","",TEXT(F19,"MMM")) -> Sep | I19: =F19+56 -> 45982 | K19: Private | M19: 1100000 | N19: 1150000 | Q19: EFT | R19: Y | S19: 4900 | T19: =IF(S19="","",IF(Q19="EFT",S19/11,"")) -> 445.45455 | U19: =IF(T19="",S19,S19-T19) -> 4454.5455 | V19: N | W19: =IF(V19="Y",U19*0.1,"") | Y19: Small | Z19: 0.45833333 | AA19: 0.72916667 | AB19: Y | AC19: =IF(AB19="Y",(AA19-Z19)+(0.5/24),(AA19-Z19)) -> 0.29166667 | AD19: =IF(Y19="small",AC19*24*$AN$2,AC19*24*$AO$2) -> 770 | AE19: =IF(AD19="","",AD19/11) -> 70 | AF19: Y
A20: 19 | B20: 11 Melaleuca Dr | C20: Clarinda | D20: Ray White, Clayton | E20: Michael Renzella | F20: 45930 | G20: 45930 | H20: =IF(F20="","",TEXT(F20,"MMM")) -> Sep | I20: =F20+56 -> 45986 | K20: Auction | L20: 45962 | M20: 880000 | N20: 950000 | Q20: EFT | R20: Y | S20: 2770 | T20: =IF(S20="","",IF(Q20="EFT",S20/11,"")) -> 251.81818 | U20: =IF(T20="",S20,S20-T20) -> 2518.1818 | V20: Y | W20: =IF(V20="Y",U20*0.1,"") -> 251.81818 | Y20: Small | Z20: 0.58333333 | AA20: 0.66666667 | AB20: Y | AC20: =IF(AB20="Y",(AA20-Z20)+(0.5/24),(AA20-Z20)) -> 0.10416667 | AD20: =IF(Y20="small",AC20*24*$AN$2,AC20*24*$AO$2) -> 275 | AE20: =IF(AD20="","",AD20/11) -> 25 | AF20: Y
A21: 20 | B21: 53 Minindee Rd | C21: Manor Lakes | D21: Eview Real Estate | E21: Mahesh Krishna | F21: 45938 | G21: 45940 | H21: =IF(F21="","",TEXT(F21,"MMM")) -> Oct | I21: =F21+56 -> 45994 | K21: Private | M21: 769000 | N21: 789000 | Q21: EFT | R21: Y | S21: 3500 | T21: =IF(S21="","",IF(Q21="EFT",S21/11,"")) -> 318.18182 | U21: =IF(T21="",S21,S21-T21) -> 3181.8182 | V21: N | W21: =IF(V21="Y",U21*0.1,"") | Y21: Small | Z21: 0.54166667 | AA21: 0.6875 | AB21: Y | AC21: =IF(AB21="Y",(AA21-Z21)+(0.5/24),(AA21-Z21)) -> 0.16666667 | AD21: =IF(Y21="small",AC21*24*$AN$2,AC21*24*$AO$2) -> 440 | AE21: =IF(AD21="","",AD21/11) -> 40 | AF21: Y
A22: 21 | B22: 1/18 Wordsworth Ave | C22: Clayton South | D22: Ray White, Clayton | E22: Michael Renzella | F22: 45959 | G22: 45960 | H22: =IF(F22="","",TEXT(F22,"MMM")) -> Oct | I22: =F22+56 -> 46015 | K22: Auction | L22: 45990 | M22: 550000 | N22: 590000 | Q22: EFT | R22: N | S22: 2310 | T22: =IF(S22="","",IF(Q22="EFT",S22/11,"")) -> 210 | U22: =IF(T22="",S22,S22-T22) -> 2100 | V22: Y | W22: =IF(V22="Y",U22*0.1,"") -> 210 | Y22: Small | Z22: 0.5 | AA22: 0.58333333 | AB22: N | AC22: =IF(AB22="Y",(AA22-Z22)+(0.5/24),(AA22-Z22)) -> 0.083333333 | AD22: 242 | AE22: =IF(AD22="","",AD22/11) -> 22 | AF22: Y | AH22: Gagan Transport

Sheet Master Price
A1: Description | B1: Unit Cost | C1: Qty | D1: Total Cost | E1: Actual Cost
A2: Master Bedroom | B2: 450 | C2: 1 | D2: =B2*C2 -> 450 | E2: 450
A3: Guest Bedroom | B3: 350 | C3: 3 | D3: =B3*C3 -> 1050 | E3: 350
A4: Living | B4: 450 | C4: 2 | D4: =B4*C4 -> 900 | E4: 450 | H4: Incl GST | I4: Excl. GST | J4: GST
A5: Dining | B5: 350 | C5: 1 | D5: =B5*C5 -> 350 | E5: 350 | F5: Furniture Rental | H5: =D18-H7-H6 -> 1625 | I5: =MROUND(H5/11*10,1) -> 1477 | J5: =MROUND(H5/11,1) -> 148
A6: Kitchen | B6: 100 | C6: 1 | D6: =B6*C6 -> 100 | E6: 100 | F6: Design & Installation Charges | G6: House | H6: =IF(G6="House",715,572) -> 715 | I6: =MROUND(H6/11*10,1) -> 650 | J6: =MROUND(H6/11,1) -> 65
A7: Alfresco | B7: 150 | C7: 1 | D7: =B7*C7 -> 150 | E7: 100 | F7: Transport (Delivery and Pickup) | G7: Large | H7: =IF(G7="Small", 550,860) -> 860 | I7: =MROUND(H7/11*10,1) -> 782 | J7: =MROUND(H7/11,1) -> 78
A8: Bath | B8: 50 | C8: 2 | D8: =B8*C8 -> 100 | E8: 50 | F8: Total Rental Rate | H8: =SUM(H5:H7) -> 3200 | I8: =SUM(I5:I7) -> 2909 | J8: =SUM(J5:J7) -> 291
A9: Hallway Table | B9: 100 | C9: 1 | D9: =B9*C9 -> 100 | E9: 100
A10: Study | B10: 300 | D10: =B10*C10 -> 0 | E10: 300
A11: Small Living | B11: 300 | D11: =B11*C11 -> 0 | E11: 300
A13: Sub Total | D13: =SUM(D2:D11) -> 3200 | F13: Required Amount
A14: Added percentage | D14: =IF(B14="",0,D13*B14) -> 0
A15: Reduced percentage | D15: =IF(B15="",0,D13*B15) -> 0 | F15: Reduced percentage | H15: =1-(H13/D18) -> 1
A16: Referral | D16: =IF(B16="",0,(D13+D14-D15)*B16) -> 0
A18: Total | D18: =MROUND(D13+D14-D15+D16,10) -> 3200
A19: GST | D19: =D18/11 -> 290.90909

Sheet Transport Only
D1: Truck
G2: Total Paid | H2: =SUBTOTAL(9,H4:H105) -> 2622
A3: Date | B3: Month | C3: Truck | D3: Time In | E3: Time Out | F3: Call Out Fee | G3: Total Hours | H3: Gross | I3: GST | J3: Paid | K3: Invoice No. | L3: Notes
A4: 45864 | B4: =TEXT(A4,"MMM") -> Jul | C4: Big | D4: 0.42708333 | E4: 0.61458333 | F4: Y | G4: =IF(F4="Y",(E4-D4)+(0.5/24),(E4-D4)) -> 0.20833333 | H4: =IF(C4="small",G4*24*'Staging Jobs'!$AN$2,G4*24*'Staging Jobs'!$AO$2) -> 715 | I4: =H4/11 -> 65 | J4: Y | K4: 00223
A5: 45865 | B5: =TEXT(A5,"MMM") -> Jul | C5: Big | D5: 0.45833333 | E5: 0.60416667 | F5: Y | G5: =IF(F5="Y",(E5-D5)+(0.5/24),(E5-D5)) -> 0.16666667 | H5: =IF(C5="small",G5*24*'Staging Jobs'!$AN$2,G5*24*'Staging Jobs'!$AO$2) -> 572 | I5: =H5/11 -> 52 | J5: Y
A6: 45892 | B6: =TEXT(A6,"MMM") -> Aug | C6: Small | D6: 0.45833333 | E6: 0.54166667 | F6: Y | G6: =IF(F6="Y",(E6-D6)+(0.5/24),(E6-D6)) -> 0.10416667 | H6: =IF(C6="small",G6*24*'Staging Jobs'!$AN$2,G6*24*'Staging Jobs'!$AO$2) -> 275 | I6: =H6/11 -> 25 | J6: Y
A7: 45914 | B7: =TEXT(A7,"MMM") -> Sep | C7: Small | D7: 0.41666667 | E7: 0.45833333 | G7: =IF(F7="Y",(E7-D7)+(0.5/24),(E7-D7)) -> 0.041666667 | H7: 70 | I7: =H7/11 -> 6.3636364 | J7: Y | L7: Racking delivery
A8: 45921 | B8: =TEXT(A8,"MMM") -> Sep | C8: Small | D8: 0.70833333 | E8: 0.79166667 | F8: Y | G8: =IF(F8="Y",(E8-D8)+(0.5/24),(E8-D8)) -> 0.10416667 | H8: =IF(C8="small",G8*24*'Staging Jobs'!$AN$2,G8*24*'Staging Jobs'!$AO$2) -> 275 | I8: =H8/11 -> 25 | J8: Y | L8: Removed 2/16 Risdon Dr
A9: 45923 | B9: =TEXT(A9,"MMM") -> Sep | C9: Small | D9: 0.375 | E9: 0.5 | F9: Y | G9: =IF(F9="Y",(E9-D9)+(0.5/24),(E9-D9)) -> 0.14583333 | H9: =IF(C9="small",G9*24*'Staging Jobs'!$AN$2,G9*24*'Staging Jobs'!$AO$2) -> 385 | I9: =H9/11 -> 35 | J9: Y | L9: Delivered the rack and moved one load from Springvale to Clayton Warehouse
A10: 45962 | B10: =TEXT(A10,"MMM") -> Nov | C10: Small | D10: 0.41666667 | E10: 0.52083333 | F10: Y | G10: =IF(F10="Y",(E10-D10)+(0.5/24),(E10-D10)) -> 0.125 | H10: =IF(C10="small",G10*24*'Staging Jobs'!$AN$2,G10*24*'Staging Jobs'!$AO$2) -> 330 | I10: =H10/11 -> 30
B11: =TEXT(A11,"MMM") -> Jan | G11: =IF(F11="Y",(E11-D11)+(0.5/24),(E11-D11)) -> 0 | H11: =IF(C11="small",G11*24*'Staging Jobs'!$AN$2,G11*24*'Staging Jobs'!$AO$2) -> 0 | I11: =H11/11 -> 0
B12: =TEXT(A12,"MMM") -> Jan | G12: =IF(F12="Y",(E12-D12)+(0.5/24),(E12-D12)) -> 0 | H12: =IF(C12="small",G12*24*'Staging Jobs'!$AN$2,G12*24*'Staging Jobs'!$AO$2) -> 0 | I12: =H12/11 -> 0
B13: =TEXT(A13,"MMM") -> Jan | G13: =IF(F13="Y",(E13-D13)+(0.5/24),(E13-D13)) -> 0 | H13: =IF(C13="small",G13*24*'Staging Jobs'!$AN$2,G13*24*'Staging Jobs'!$AO$2) -> 0 | I13: =H13/11 -> 0
B14: =TEXT(A14,"MMM") -> Jan | G14: =IF(F14="Y",(E14-D14)+(0.5/24),(E14-D14)) -> 0 | H14: =IF(C14="small",G14*24*'Staging Jobs'!$AN$2,G14*24*'Staging Jobs'!$AO$2) -> 0 | I14: =H14/11 -> 0
